{"lang": "en", "deleted": false, "text": "NSA Deputy Director Ledgett: On the Defense Industrial Base sharing project: \"That might be a model that we can build on in the future.\"", "created_at": "Thu Sep 18 15:54:59 +0000 2014", "hashtags": [], "user_mentions": [], "source": "<a href=\"http://twitter.com\" rel=\"nofollow\">Twitter Web Client</a>", "id_str": "512630873574080512", "urls": [], "retrieved": "2017-04-17--14-12-34", "retweet_count": 8, "id": 512630873574080512, "favorite_count": 6, "user": {"id": 2248872301}}