{"lang": "en", "media": [{"expanded_url": "https://twitter.com/NSAGov/status/636552202710986753/photo/1", "display_url": "pic.twitter.com/3Uzo065CJx", "url": "http://t.co/3Uzo065CJx", "media_url_https": "https://pbs.twimg.com/media/CNVhakAU8AADYNj.jpg", "type": "photo", "id": 636522031312334848, "media_url": "http://pbs.twimg.com/media/CNVhakAU8AADYNj.jpg"}], "deleted": false, "retrieved": "2017-04-17--14-12-33", "created_at": "Wed Aug 26 14:54:06 +0000 2015", "hashtags": [{"text": "WomensEquality"}, {"text": "math"}], "user_mentions": [], "source": "<a href=\"https://about.twitter.com/products/tweetdeck\" rel=\"nofollow\">TweetDeck</a>", "id_str": "636552202710986753", "urls": [{"url": "http://t.co/98lo4GIRYf", "expanded_url": "http://bit.ly/1USS8M7"}], "text": "For #WomensEquality Day NSA hosted a #math talk on work of 1st woman to win the Fields Medal http://t.co/98lo4GIRYf http://t.co/3Uzo065CJx", "retweet_count": 29, "id": 636552202710986753, "favorite_count": 27, "user": {"id": 2248872301}}