{"lang": "en", "media": [{"expanded_url": "https://twitter.com/NSAGov/status/755051265298542593/photo/1", "display_url": "pic.twitter.com/LufN9OVIGQ", "url": "https://t.co/LufN9OVIGQ", "media_url_https": "https://pbs.twimg.com/media/Cnps0OWXEAAuO0d.jpg", "type": "photo", "id": 755035531998859264, "media_url": "http://pbs.twimg.com/media/Cnps0OWXEAAuO0d.jpg"}], "deleted": false, "retrieved": "2017-04-17--14-12-32", "created_at": "Mon Jul 18 14:47:04 +0000 2016", "hashtags": [{"text": "GenCyber"}], "user_mentions": [], "source": "<a href=\"https://about.twitter.com/products/tweetdeck\" rel=\"nofollow\">TweetDeck</a>", "id_str": "755051265298542593", "urls": [{"url": "https://t.co/NjABeMaYnF", "expanded_url": "http://www.gen-cyber.com"}], "text": "Students and teachers are having a blast this summer at #GenCyber camps! Find out more at: https://t.co/NjABeMaYnF https://t.co/LufN9OVIGQ", "retweet_count": 51, "id": 755051265298542593, "favorite_count": 83, "user": {"id": 2248872301}}