{"lang": "en", "deleted": false, "text": "FBI News Blog: Stay Connected: New and Improved FBI Widgets: Do you run a website or blog? Have a social media... http://t.co/Lqzl4Afaui", "created_at": "Thu Jul 25 16:36:51 +0000 2013", "hashtags": [], "user_mentions": [], "source": "<a href=\"http://twitterfeed.com\" rel=\"nofollow\">twitterfeed</a>", "id_str": "360438505551306752", "urls": [{"url": "http://t.co/Lqzl4Afaui", "expanded_url": "http://1.usa.gov/16ekKoS"}], "retrieved": "2017-04-17--14-14-16", "retweet_count": 21, "id": 360438505551306752, "favorite_count": 14, "user": {"id": 17629860}}