{"lang": "en", "deleted": false, "text": "FBI News Blog: Public Corruption: Inside the Kwame Kilpatrick Case: When Kwame Kilpatrick became mayor of Detr... http://t.co/fU4l103Waf", "created_at": "Tue Nov 12 17:12:11 +0000 2013", "hashtags": [], "user_mentions": [], "source": "<a href=\"http://twitterfeed.com\" rel=\"nofollow\">twitterfeed</a>", "id_str": "400310065552297984", "urls": [{"url": "http://t.co/fU4l103Waf", "expanded_url": "http://1.usa.gov/1ck4dmk"}], "retrieved": "2017-04-17--14-14-15", "retweet_count": 29, "id": 400310065552297984, "favorite_count": 11, "user": {"id": 17629860}}