{"lang": "en", "deleted": false, "text": "FBI News Blog: Unearthing the Truth: FBI Jacksonville\u2019s Evidence Response Team Digs Up the Past: It wasn\u2019t exa... http://t.co/qf3CyJBqoa", "created_at": "Fri Nov 15 22:55:41 +0000 2013", "hashtags": [], "user_mentions": [], "source": "<a href=\"http://twitterfeed.com\" rel=\"nofollow\">twitterfeed</a>", "id_str": "401483673947496448", "urls": [{"url": "http://t.co/qf3CyJBqoa", "expanded_url": "http://1.usa.gov/18BA2Vs"}], "retrieved": "2017-04-17--14-14-15", "retweet_count": 18, "id": 401483673947496448, "favorite_count": 7, "user": {"id": 17629860}}