{"lang": "en", "deleted": false, "text": "Manhattan U.S. Attorney and FBI Assistant Director in Charge Announce Filing of Criminal Charges Against ... http://t.co/HHZCr6V5ot #FBI", "created_at": "Tue Jan 07 21:32:00 +0000 2014", "hashtags": [{"text": "FBI"}], "user_mentions": [], "source": "<a href=\"http://twitterfeed.com\" rel=\"nofollow\">twitterfeed</a>", "id_str": "420669169739124736", "urls": [{"url": "http://t.co/HHZCr6V5ot", "expanded_url": "http://1.usa.gov/1a5ydRB"}], "retrieved": "2017-04-17--14-14-15", "retweet_count": 22, "id": 420669169739124736, "favorite_count": 17, "user": {"id": 17629860}}