{"lang": "en", "deleted": false, "text": "The new edition of the @FBILEB includes articles on law enforcement challenges for the future and more  https://t.co/A8CAINEcrD", "created_at": "Wed Feb 10 21:49:37 +0000 2016", "hashtags": [], "user_mentions": [{"screen_name": "FBILEB", "id": 1408879261, "name": "FBI LEB"}], "source": "<a href=\"http://www.fbi.gov\" rel=\"nofollow\">GovTweetManager</a>", "id_str": "697537933243478017", "urls": [{"url": "https://t.co/A8CAINEcrD", "expanded_url": "https://leb.fbi.gov/"}], "retrieved": "2017-04-17--14-14-14", "retweet_count": 63, "id": 697537933243478017, "favorite_count": 91, "user": {"id": 17629860}}