{"lang": "en", "deleted": false, "text": "Learn how the #FBI combats #HumanTrafficking &amp; works with our partners across the globe #EndTrafficking https://t.co/OcHbEZhGci", "created_at": "Mon Jan 09 17:33:42 +0000 2017", "hashtags": [{"text": "FBI"}, {"text": "HumanTrafficking"}, {"text": "EndTrafficking"}], "user_mentions": [], "source": "<a href=\"http://www.fbi.gov\" rel=\"nofollow\">GovTweetManager</a>", "id_str": "818511077570842629", "urls": [{"url": "https://t.co/OcHbEZhGci", "expanded_url": "https://www.fbi.gov/investigate/civil-rights/human-trafficking"}], "retrieved": "2017-04-17--14-14-14", "retweet_count": 212, "id": 818511077570842629, "favorite_count": 252, "user": {"id": 17629860}}