{"lang": "en", "deleted": false, "text": "This is the second time in as many years the world has relied upon #CJEU to defend digital rights. Thank you Europe. #DataRetentionDirective", "created_at": "Tue Oct 06 13:16:59 +0000 2015", "hashtags": [{"text": "CJEU"}, {"text": "DataRetentionDirective"}], "user_mentions": [], "source": "<a href=\"http://twitter.com\" rel=\"nofollow\">Twitter Web Client</a>", "id_str": "651385667268837376", "urls": [], "retrieved": "2017-04-17--14-14-36", "retweet_count": 1526, "id": 651385667268837376, "favorite_count": 2004, "user": {"id": 2916305152}}