{"lang": "en", "deleted": false, "text": "I could go on forever. It is an endless parade of falsity so unbelievable it comes across as parody. Yet unintentionally exonerating:", "created_at": "Thu Dec 22 16:32:45 +0000 2016", "hashtags": [], "user_mentions": [], "source": "<a href=\"http://twitter.com\" rel=\"nofollow\">Twitter Web Client</a>", "in_reply_to_status_id": 811971580179992581, "id_str": "811972754484428801", "in_reply_to_screen_name": "Snowden", "user": {"id": 2916305152}, "urls": [], "retrieved": "2017-04-17--14-14-35", "retweet_count": 318, "id": 811972754484428801, "favorite_count": 864, "in_reply_to_user_id": 2916305152}