{"lang": "en", "deleted": false, "text": "@Bilalhb @Timcast There's significant violence in US unrelated to religion. And this: https://t.co/vGFe5jUKLo - &amp; that's not what Trump said", "created_at": "Mon Feb 27 13:07:54 +0000 2017", "hashtags": [], "user_mentions": [{"screen_name": "Bilalhb", "id": 38692090, "name": "Bilal \u2d31\u2d49\u2d4d\u2d30\u2d4d \u200f"}, {"screen_name": "Timcast", "id": 27000730, "name": "Tim Pool"}], "source": "<a href=\"http://twitter.com\" rel=\"nofollow\">Twitter Web Client</a>", "in_reply_to_status_id": 836200824510550017, "id_str": "836201189360414722", "in_reply_to_screen_name": "Bilalhb", "user": {"id": 16076032}, "urls": [{"url": "https://t.co/vGFe5jUKLo", "expanded_url": "http://www.motherjones.com/politics/2017/01/fox-news-quebec-city-mosque-attack-right-wing-shooter"}], "retrieved": "2017-04-17--14-12-17", "retweet_count": 13, "id": 836201189360414722, "favorite_count": 29, "in_reply_to_user_id": 38692090}