{"lang": "en", "deleted": false, "text": "@Jordanandre1 @Grant_Case OK, if you feel like Dem Party has great leaders, strategies &amp; messaging, keep them. Doesn't seem rational to me.", "created_at": "Fri Mar 03 20:06:00 +0000 2017", "hashtags": [], "user_mentions": [{"screen_name": "Jordanandre1", "id": 21913686, "name": "Yonny Hammer"}, {"screen_name": "Grant_Case", "id": 15202170, "name": "Grant_Case"}], "source": "<a href=\"http://twitter.com\" rel=\"nofollow\">Twitter Web Client</a>", "in_reply_to_status_id": 837755627095093248, "id_str": "837755961792167937", "in_reply_to_screen_name": "Jordanandre1", "user": {"id": 16076032}, "urls": [], "retrieved": "2017-04-17--14-12-17", "retweet_count": 8, "id": 837755961792167937, "favorite_count": 34, "in_reply_to_user_id": 21913686}