{"lang": "pt", "deleted": false, "text": "@migsaugusto @davidmirandario Sim, isso \u00e9 interessante. Mas est\u00e1 acontecendo em muitos estados em todo o pa\u00eds.", "created_at": "Wed Mar 08 01:43:33 +0000 2017", "hashtags": [], "user_mentions": [{"screen_name": "migsaugusto", "id": 34902153, "name": "Miguel Augusto"}, {"screen_name": "davidmirandario", "id": 2479861125, "name": "David Miranda"}], "source": "<a href=\"http://twitter.com\" rel=\"nofollow\">Twitter Web Client</a>", "in_reply_to_status_id": 839290182784413696, "id_str": "839290458278875136", "in_reply_to_screen_name": "migsaugusto", "user": {"id": 16076032}, "urls": [], "retrieved": "2017-04-17--14-12-17", "id": 839290458278875136, "favorite_count": 1, "in_reply_to_user_id": 34902153}