{"lang": "en", "deleted": false, "text": "It's ironic that this is in Mike Allen's new outlet but it is obviously a part of why people distrust US media https://t.co/0v4G5BtcWw", "created_at": "Thu Mar 09 18:50:02 +0000 2017", "hashtags": [], "user_mentions": [], "source": "<a href=\"http://twitter.com\" rel=\"nofollow\">Twitter Web Client</a>", "id_str": "839911171868229632", "urls": [{"url": "https://t.co/0v4G5BtcWw", "expanded_url": "https://www.axios.com/half-of-americans-say-journalists-shouldnt-cite-anonymous-sources-2307853582.html"}], "retrieved": "2017-04-17--14-12-17", "retweet_count": 79, "id": 839911171868229632, "favorite_count": 130, "user": {"id": 16076032}}