{"lang": "en", "retweeted_status": {"lang": "en", "text": "Bernie Sanders: \"How can anyone not conclude that the Democratic agenda and approach has been a failure?\u201d https://t.co/rHP0RDvwnx", "created_at": "Fri Mar 10 00:00:20 +0000 2017", "hashtags": [], "user_mentions": [], "source": "<a href=\"http://twitter.com\" rel=\"nofollow\">Twitter Web Client</a>", "id_str": "839989260837113856", "urls": [], "media": [{"expanded_url": "https://twitter.com/matthewstoller/status/839989260837113856/photo/1", "display_url": "pic.twitter.com/rHP0RDvwnx", "url": "https://t.co/rHP0RDvwnx", "media_url_https": "https://pbs.twimg.com/media/C6g9opxVwAA2wxy.jpg", "type": "photo", "id": 839989099121459200, "media_url": "http://pbs.twimg.com/media/C6g9opxVwAA2wxy.jpg"}], "retweet_count": 3611, "id": 839989260837113856, "favorite_count": 6367, "user": {"id": 2030711}}, "deleted": false, "text": "RT @matthewstoller: Bernie Sanders: \"How can anyone not conclude that the Democratic agenda and approach has been a failure?\u201d https://t.co/\u2026", "created_at": "Fri Mar 10 01:29:28 +0000 2017", "hashtags": [], "user_mentions": [{"screen_name": "matthewstoller", "id": 2030711, "name": "Matt Stoller"}], "source": "<a href=\"http://twitter.com\" rel=\"nofollow\">Twitter Web Client</a>", "id_str": "840011691945578496", "urls": [], "retrieved": "2017-04-17--14-12-17", "retweet_count": 3611, "id": 840011691945578496, "user": {"id": 16076032}}