{"lang": "en", "media": [{"expanded_url": "https://twitter.com/ggreenwald/status/841629151794757632/photo/1", "display_url": "pic.twitter.com/EVSN48St6a", "url": "https://t.co/EVSN48St6a", "media_url_https": "https://pbs.twimg.com/media/C64RPjZWwAA-mn2.jpg", "type": "photo", "id": 841629139262160896, "media_url": "http://pbs.twimg.com/media/C64RPjZWwAA-mn2.jpg"}], "deleted": false, "retrieved": "2017-04-17--14-12-17", "created_at": "Tue Mar 14 12:36:41 +0000 2017", "hashtags": [], "user_mentions": [{"screen_name": "Tekneek", "id": 10282862, "name": "Brian Greer"}, {"screen_name": "lawfare", "id": 721058335437516806, "name": "Lawfare"}], "source": "<a href=\"http://twitter.com\" rel=\"nofollow\">Twitter Web Client</a>", "in_reply_to_status_id": 841628409096740864, "id_str": "841629151794757632", "in_reply_to_screen_name": "Tekneek", "user": {"id": 16076032}, "urls": [{"url": "https://t.co/yNJFGXuNog", "expanded_url": "https://lawfareblog.com/malevolence-tempered-incompetence-trumps-horrifying-executive-order-refugees-and-visas"}], "text": "@Tekneek I've long read @Lawfare &amp; still do but I doubt they'd dispute that characterization https://t.co/yNJFGXuNog https://t.co/EVSN48St6a", "id": 841629151794757632, "favorite_count": 5, "in_reply_to_user_id": 10282862}