{"lang": "en", "retweeted_status": {"lang": "en", "truncated": true, "text": "Our 300th episode: @ggreenwald on Trump's presidency, #FakeNews &amp; American journalism in the new era\u2026 https://t.co/J6wJxToRDX", "created_at": "Fri Mar 31 10:08:26 +0000 2017", "hashtags": [{"text": "FakeNews"}], "user_mentions": [{"screen_name": "ggreenwald", "id": 16076032, "name": "Glenn Greenwald"}], "source": "<a href=\"https://about.twitter.com/products/tweetdeck\" rel=\"nofollow\">TweetDeck</a>", "id_str": "847752439197569024", "urls": [{"url": "https://t.co/J6wJxToRDX", "expanded_url": "https://twitter.com/i/web/status/847752439197569024"}], "retweet_count": 91, "id": 847752439197569024, "favorite_count": 192, "user": {"id": 15903326}}, "deleted": false, "text": "RT @TiloJung: Our 300th episode: @ggreenwald on Trump's presidency, #FakeNews &amp; American journalism in the new era https://t.co/BX5Cehvd1d\u2026", "created_at": "Fri Mar 31 11:37:18 +0000 2017", "hashtags": [{"text": "FakeNews"}], "user_mentions": [{"screen_name": "TiloJung", "id": 15903326, "name": "Tilo Jung"}, {"screen_name": "ggreenwald", "id": 16076032, "name": "Glenn Greenwald"}], "source": "<a href=\"http://twitter.com\" rel=\"nofollow\">Twitter Web Client</a>", "id_str": "847774804153442304", "urls": [{"url": "https://t.co/BX5Cehvd1d", "expanded_url": "https://youtu.be/xbNRLemflGU"}], "retrieved": "2017-04-17--14-12-16", "retweet_count": 91, "id": 847774804153442304, "user": {"id": 16076032}}