{"lang": "pt", "deleted": false, "text": "Apresentada PL do uso de banheiro pela identidade de g\u00eanero - new bill on bathroom access from @davidmirandario https://t.co/N1u5yiNQKu", "created_at": "Wed Apr 05 16:19:39 +0000 2017", "hashtags": [], "user_mentions": [{"screen_name": "davidmirandario", "id": 2479861125, "name": "David Miranda"}], "source": "<a href=\"http://twitter.com\" rel=\"nofollow\">Twitter Web Client</a>", "id_str": "849657796471779328", "urls": [{"url": "https://t.co/N1u5yiNQKu", "expanded_url": "http://www.band.uol.com.br/m/conteudo.asp?id=100000852293&programa=cidades"}], "retrieved": "2017-04-17--14-12-16", "retweet_count": 12, "id": 849657796471779328, "favorite_count": 17, "user": {"id": 16076032}}