{"lang": "en", "deleted": false, "text": "New York @SenSchumer might as well have been grown in a lab to be exactly the wrong face for opposition to Trump. https://t.co/6Lss4joUAs", "created_at": "Mon Nov 14 21:51:06 +0000 2016", "hashtags": [], "user_mentions": [{"screen_name": "SenSchumer", "id": 17494010, "name": "Chuck Schumer"}], "source": "<a href=\"http://www.socialflow.com\" rel=\"nofollow\">SocialFlow</a>", "id_str": "798282133370454016", "urls": [{"url": "https://t.co/6Lss4joUAs", "expanded_url": "https://interc.pt/2eU5OGY"}], "retrieved": "2017-04-17--14-16-08", "retweet_count": 128, "id": 798282133370454016, "favorite_count": 134, "user": {"id": 2329066872}}