{"lang": "en", "deleted": false, "text": "Trump drains a tiny corner of the swamp as he ships in more alligators and anacondas to wallow in the rest of it. https://t.co/saJCe6A4jK", "created_at": "Fri Nov 18 14:44:57 +0000 2016", "hashtags": [], "user_mentions": [], "source": "<a href=\"http://www.socialflow.com\" rel=\"nofollow\">SocialFlow</a>", "id_str": "799624439168110592", "urls": [{"url": "https://t.co/saJCe6A4jK", "expanded_url": "https://interc.pt/2f9cswk"}], "retrieved": "2017-04-17--14-16-08", "retweet_count": 60, "id": 799624439168110592, "favorite_count": 69, "user": {"id": 2329066872}}