{"lang": "en", "deleted": false, "text": "The supreme religion of the U.S. press corps is power; the more Trump exhibits, the more submissive they will get. https://t.co/A4QgoXOlCF", "created_at": "Sun Nov 27 21:13:17 +0000 2016", "hashtags": [], "user_mentions": [], "source": "<a href=\"http://www.socialflow.com\" rel=\"nofollow\">SocialFlow</a>", "id_str": "802983658307067909", "urls": [{"url": "https://t.co/A4QgoXOlCF", "expanded_url": "https://interc.pt/2g8eNGg"}], "retrieved": "2017-04-17--14-16-08", "retweet_count": 277, "id": 802983658307067909, "favorite_count": 305, "user": {"id": 2329066872}}