{"lang": "en", "media": [{"expanded_url": "https://twitter.com/theintercept/status/806218046750781440/photo/1", "display_url": "pic.twitter.com/BmZiccbwbQ", "url": "https://t.co/BmZiccbwbQ", "media_url_https": "https://pbs.twimg.com/media/CzBDCdMWEAAKUu0.jpg", "type": "photo", "id": 806218042774523904, "media_url": "http://pbs.twimg.com/media/CzBDCdMWEAAKUu0.jpg"}], "deleted": false, "retrieved": "2017-04-17--14-16-08", "created_at": "Tue Dec 06 19:25:35 +0000 2016", "hashtags": [], "user_mentions": [], "source": "<a href=\"http://www.socialflow.com\" rel=\"nofollow\">SocialFlow</a>", "id_str": "806218046750781440", "urls": [{"url": "https://t.co/RbcF9FgC7T", "expanded_url": "https://interc.pt/2gO7beN"}], "text": "Slavery as a tourist attraction reveals how Brazil naturalizes its prejudices. https://t.co/RbcF9FgC7T https://t.co/BmZiccbwbQ", "retweet_count": 82, "id": 806218046750781440, "favorite_count": 36, "user": {"id": 2329066872}}