{"lang": "en", "deleted": false, "text": "Bolton organized the firing of the head of the OPCW so it couldn't prove a big chunk of the case for war was wrong. https://t.co/opWy1n2IDo", "created_at": "Thu Dec 15 21:29:02 +0000 2016", "hashtags": [], "user_mentions": [], "source": "<a href=\"http://www.socialflow.com\" rel=\"nofollow\">SocialFlow</a>", "id_str": "809510603287044097", "urls": [{"url": "https://t.co/opWy1n2IDo", "expanded_url": "https://interc.pt/2hz3tXl"}], "retrieved": "2017-04-17--14-16-08", "retweet_count": 98, "id": 809510603287044097, "favorite_count": 73, "user": {"id": 2329066872}}