{"lang": "en", "deleted": false, "text": "One of Brazil\u2019s few incorruptible figures died at a key moment in corruption investigation. https://t.co/gqtSHNKaiX", "created_at": "Fri Jan 20 14:50:30 +0000 2017", "hashtags": [], "user_mentions": [], "source": "<a href=\"http://www.socialflow.com\" rel=\"nofollow\">SocialFlow</a>", "id_str": "822456270531784704", "urls": [{"url": "https://t.co/gqtSHNKaiX", "expanded_url": "https://interc.pt/2jHqgkv"}], "retrieved": "2017-04-17--14-16-08", "retweet_count": 369, "id": 822456270531784704, "favorite_count": 316, "user": {"id": 2329066872}}