{"lang": "en", "deleted": false, "text": "Gina Haspel, directly involved in the most grotesque torture abuses, will now help lead the CIA. https://t.co/nQYa5u6d9I", "created_at": "Thu Feb 02 23:20:11 +0000 2017", "hashtags": [], "user_mentions": [], "source": "<a href=\"http://www.socialflow.com\" rel=\"nofollow\">SocialFlow</a>", "id_str": "827295581836079104", "urls": [{"url": "https://t.co/nQYa5u6d9I", "expanded_url": "https://interc.pt/2kuT5RS"}], "retrieved": "2017-04-17--14-16-07", "retweet_count": 449, "id": 827295581836079104, "favorite_count": 236, "user": {"id": 2329066872}}