{"lang": "en", "deleted": false, "text": "Gov. Abbott vowed to strip Austin of funding unless it illegally detains people suspected of immigration violations. https://t.co/wbLVFlvOzm", "created_at": "Fri Feb 03 20:28:25 +0000 2017", "hashtags": [], "user_mentions": [], "source": "<a href=\"http://www.socialflow.com\" rel=\"nofollow\">SocialFlow</a>", "id_str": "827614743322099714", "urls": [{"url": "https://t.co/wbLVFlvOzm", "expanded_url": "https://interc.pt/2l4obNn"}], "retrieved": "2017-04-17--14-16-07", "retweet_count": 183, "id": 827614743322099714, "favorite_count": 116, "user": {"id": 2329066872}}