{"lang": "en", "retweeted_status": {"lang": "en", "text": "Could you be a terrorist? Take the FBI quiz. https://t.co/64YF5KGDVF by @coracurrier @mazmhussain", "created_at": "Mon Feb 13 15:57:47 +0000 2017", "hashtags": [], "user_mentions": [{"screen_name": "coracurrier", "id": 379331236, "name": "Cora Currier"}, {"screen_name": "MazMHussain", "id": 84816752, "name": "Murtaza Hussain"}], "source": "<a href=\"http://twitter.com\" rel=\"nofollow\">Twitter Web Client</a>", "id_str": "831170513452068864", "urls": [{"url": "https://t.co/64YF5KGDVF", "expanded_url": "https://interc.pt/2lBCQmQ"}], "retweet_count": 88, "id": 831170513452068864, "favorite_count": 74, "user": {"id": 21120847}}, "deleted": false, "text": "RT @weinbergersa: Could you be a terrorist? Take the FBI quiz. https://t.co/64YF5KGDVF by @coracurrier @mazmhussain", "created_at": "Mon Feb 13 16:51:55 +0000 2017", "hashtags": [], "user_mentions": [{"screen_name": "weinbergersa", "id": 21120847, "name": "Sharon Weinberger"}, {"screen_name": "coracurrier", "id": 379331236, "name": "Cora Currier"}, {"screen_name": "MazMHussain", "id": 84816752, "name": "Murtaza Hussain"}], "source": "<a href=\"https://about.twitter.com/products/tweetdeck\" rel=\"nofollow\">TweetDeck</a>", "id_str": "831184137981657088", "urls": [{"url": "https://t.co/64YF5KGDVF", "expanded_url": "https://interc.pt/2lBCQmQ"}], "retrieved": "2017-04-17--14-16-07", "retweet_count": 88, "id": 831184137981657088, "user": {"id": 2329066872}}