{"lang": "en", "retweeted_status": {"lang": "en", "text": "You are right @realDonaldTrump there is an increase in autism. Here's how you can help https://t.co/GjyfqThqFf", "created_at": "Fri Feb 17 04:37:13 +0000 2017", "hashtags": [], "user_mentions": [{"screen_name": "realDonaldTrump", "id": 25073877, "name": "Donald J. Trump"}], "source": "<a href=\"http://twitter.com\" rel=\"nofollow\">Twitter Web Client</a>", "id_str": "832448794323275777", "urls": [{"url": "https://t.co/GjyfqThqFf", "expanded_url": "https://interc.pt/2juNMOU"}], "retweet_count": 135, "id": 832448794323275777, "favorite_count": 165, "user": {"id": 76383589}}, "deleted": false, "text": "RT @fastlerner: You are right @realDonaldTrump there is an increase in autism. Here's how you can help https://t.co/GjyfqThqFf", "created_at": "Fri Feb 17 15:39:03 +0000 2017", "hashtags": [], "user_mentions": [{"screen_name": "fastlerner", "id": 76383589, "name": "Sharon Lerner"}, {"screen_name": "realDonaldTrump", "id": 25073877, "name": "Donald J. Trump"}], "source": "<a href=\"https://about.twitter.com/products/tweetdeck\" rel=\"nofollow\">TweetDeck</a>", "id_str": "832615349585592320", "urls": [{"url": "https://t.co/GjyfqThqFf", "expanded_url": "https://interc.pt/2juNMOU"}], "retrieved": "2017-04-17--14-16-07", "retweet_count": 135, "id": 832615349585592320, "user": {"id": 2329066872}}