{"lang": "en", "deleted": false, "text": "The White House may be breaking with Obama administration policies that were intended to limit civilian casualties. https://t.co/vgTZj3lzCY", "created_at": "Thu Mar 09 14:58:43 +0000 2017", "hashtags": [], "user_mentions": [], "source": "<a href=\"http://www.socialflow.com\" rel=\"nofollow\">SocialFlow</a>", "id_str": "839852958300966912", "urls": [{"url": "https://t.co/vgTZj3lzCY", "expanded_url": "https://interc.pt/2na1x7i"}], "retrieved": "2017-04-17--14-16-07", "retweet_count": 104, "id": 839852958300966912, "favorite_count": 63, "user": {"id": 2329066872}}