{"lang": "en", "deleted": false, "text": "For more context on Erik Prince, read this @jeremyscahill piece about him advising Trump from the shadows: https://t.co/nWD2GPmpQP", "created_at": "Tue Apr 04 17:11:02 +0000 2017", "hashtags": [], "user_mentions": [{"screen_name": "jeremyscahill", "id": 23839835, "name": "jeremy scahill"}], "source": "<a href=\"http://www.socialflow.com\" rel=\"nofollow\">SocialFlow</a>", "id_str": "849308342396874754", "urls": [{"url": "https://t.co/nWD2GPmpQP", "expanded_url": "https://interc.pt/2nTGVkQ"}], "retrieved": "2017-04-17--14-16-06", "retweet_count": 157, "id": 849308342396874754, "favorite_count": 141, "user": {"id": 2329066872}}