{"lang": "en", "deleted": false, "text": "Trump surrenders element of surprise by warning Russia of planned strike on its ally Syria https://t.co/LHgNdHnwgn by @RobertMackey", "created_at": "Fri Apr 07 13:41:13 +0000 2017", "hashtags": [], "user_mentions": [{"screen_name": "RobertMackey", "id": 17737614, "name": "Robert Mackey"}], "source": "<a href=\"http://www.socialflow.com\" rel=\"nofollow\">SocialFlow</a>", "id_str": "850342702520709121", "urls": [{"url": "https://t.co/LHgNdHnwgn", "expanded_url": "https://interc.pt/2nloTdU"}], "retrieved": "2017-04-17--14-16-06", "retweet_count": 106, "id": 850342702520709121, "favorite_count": 97, "user": {"id": 2329066872}}