{"lang": "en", "deleted": false, "text": "What really happened in 2001 when China brought down a U.S. military spy plane? https://t.co/51f92wlPQt", "created_at": "Mon Apr 10 14:38:45 +0000 2017", "hashtags": [], "user_mentions": [], "source": "<a href=\"http://www.socialflow.com\" rel=\"nofollow\">SocialFlow</a>", "id_str": "851444346461278210", "urls": [{"url": "https://t.co/51f92wlPQt", "expanded_url": "https://interc.pt/2oqtKtQ"}], "retrieved": "2017-04-17--14-16-06", "retweet_count": 95, "id": 851444346461278210, "favorite_count": 120, "user": {"id": 2329066872}}