{"lang": "en", "media": [{"expanded_url": "https://twitter.com/CIA/status/483991963893772289/photo/1", "display_url": "pic.twitter.com/USKwYTVWIO", "url": "http://t.co/USKwYTVWIO", "media_url_https": "https://pbs.twimg.com/media/Brd8IFcCAAAGuuU.jpg", "type": "photo", "id": 483991963306164224, "media_url": "http://pbs.twimg.com/media/Brd8IFcCAAAGuuU.jpg"}], "deleted": false, "retrieved": "2017-04-17--14-15-38", "created_at": "Tue Jul 01 15:14:10 +0000 2014", "hashtags": [{"text": "U2Week"}, {"text": "4July1956"}], "user_mentions": [], "source": "<a href=\"https://about.twitter.com/products/tweetdeck\" rel=\"nofollow\">TweetDeck</a>", "id_str": "483991963893772289", "urls": [], "text": "Kelly Johnson &amp; Skunk Works had prototype in 88 days; operational U-2 was on time and under budget #U2Week #4July1956 http://t.co/USKwYTVWIO", "retweet_count": 311, "id": 483991963893772289, "favorite_count": 410, "user": {"id": 2359926157}}