{"lang": "en", "deleted": false, "text": "Time capsule contained documents &amp; historical materials relating to the newly created CIA.  #cornerstone http://t.co/T2LD5xmVr6", "created_at": "Tue Nov 04 01:39:14 +0000 2014", "hashtags": [{"text": "cornerstone"}], "user_mentions": [], "source": "<a href=\"https://about.twitter.com/products/tweetdeck\" rel=\"nofollow\">TweetDeck</a>", "id_str": "529447747242323969", "urls": [{"url": "http://t.co/T2LD5xmVr6", "expanded_url": "http://1.usa.gov/1wXtaSJ"}], "retrieved": "2017-04-17--14-15-37", "retweet_count": 70, "id": 529447747242323969, "favorite_count": 107, "user": {"id": 2359926157}}