{"lang": "en", "media": [{"expanded_url": "https://twitter.com/CIA/status/584769728536653824/photo/1", "display_url": "pic.twitter.com/Zhix9XDW9D", "url": "http://t.co/Zhix9XDW9D", "media_url_https": "https://pbs.twimg.com/media/CBs20GdUoAApHXi.jpg", "type": "photo", "id": 584120845389307904, "media_url": "http://pbs.twimg.com/media/CBs20GdUoAApHXi.jpg"}], "deleted": false, "retrieved": "2017-04-17--14-15-37", "created_at": "Sun Apr 05 17:29:02 +0000 2015", "hashtags": [{"text": "HISTINT"}], "user_mentions": [], "source": "<a href=\"https://about.twitter.com/products/tweetdeck\" rel=\"nofollow\">TweetDeck</a>", "id_str": "584769728536653824", "urls": [{"url": "http://t.co/T6YesmXcLq", "expanded_url": "http://1.usa.gov/1Dq2m1G"}], "text": "ICYMI: Art Lundahl, father of imagery analysis, would have turned 100 on 1 April! #HISTINT http://t.co/T6YesmXcLq http://t.co/Zhix9XDW9D", "retweet_count": 60, "id": 584769728536653824, "favorite_count": 95, "user": {"id": 2359926157}}