{"lang": "en", "deleted": false, "text": "#Ford followed his older brother to Hollywood &amp; began his career in the movie industry as a prop man &amp; acting in his brother\u2019s silent films.", "created_at": "Thu Jun 04 19:20:09 +0000 2015", "hashtags": [{"text": "Ford"}], "user_mentions": [], "source": "<a href=\"https://about.twitter.com/products/tweetdeck\" rel=\"nofollow\">TweetDeck</a>", "id_str": "606540963821940736", "urls": [], "retrieved": "2017-04-17--14-15-37", "retweet_count": 22, "id": 606540963821940736, "favorite_count": 49, "user": {"id": 2359926157}}