{"lang": "en", "deleted": false, "text": "#OSS R&amp;A showed intel could be obtained through papers, reports, photos, maps, etc. &amp; laid foundation of modern intel research &amp; analysis.", "created_at": "Wed Jun 17 16:46:05 +0000 2015", "hashtags": [{"text": "OSS"}], "user_mentions": [], "source": "<a href=\"https://about.twitter.com/products/tweetdeck\" rel=\"nofollow\">TweetDeck</a>", "id_str": "611213233811132418", "urls": [], "retrieved": "2017-04-17--14-15-37", "retweet_count": 47, "id": 611213233811132418, "favorite_count": 76, "user": {"id": 2359926157}}