{"lang": "en", "media": [{"expanded_url": "https://twitter.com/CIA/status/643536467860434944/photo/1", "display_url": "pic.twitter.com/OVvNxb54Uy", "url": "http://t.co/OVvNxb54Uy", "media_url_https": "https://pbs.twimg.com/media/CO4yrINWwAEKuqo.jpg", "type": "photo", "id": 643507513279823873, "media_url": "http://pbs.twimg.com/media/CO4yrINWwAEKuqo.jpg"}], "deleted": false, "retrieved": "2017-04-17--14-15-37", "created_at": "Mon Sep 14 21:27:04 +0000 2015", "hashtags": [{"text": "PDB"}], "user_mentions": [{"screen_name": "LBJLibrary", "id": 113729414, "name": "LBJ Library"}], "source": "<a href=\"https://about.twitter.com/products/tweetdeck\" rel=\"nofollow\">TweetDeck</a>", "id_str": "643536467860434944", "urls": [], "text": "The President\u2019s Daily Brief (#PDB) was crafted to Johnson\u2019s specifications &amp; replaced PICL in 1964. \nCC @LBJLibrary http://t.co/OVvNxb54Uy", "retweet_count": 54, "id": 643536467860434944, "favorite_count": 81, "user": {"id": 2359926157}}