{"lang": "en", "retweeted_status": {"lang": "en", "text": "Andrew Hallman from @CIA: targets that we collect against increasingly lend themselves to a big data environment. #INTELCON", "created_at": "Tue Oct 27 18:44:12 +0000 2015", "hashtags": [{"text": "INTELCON"}], "user_mentions": [{"screen_name": "CIA", "id": 2359926157, "name": "CIA"}], "source": "<a href=\"http://twitter.com\" rel=\"nofollow\">Twitter Web Client</a>", "id_str": "659078158189244416", "urls": [], "retweet_count": 28, "id": 659078158189244416, "favorite_count": 21, "user": {"id": 19345085}}, "deleted": false, "text": "RT @gwcchs: Andrew Hallman from @CIA: targets that we collect against increasingly lend themselves to a big data environment. #INTELCON", "created_at": "Tue Oct 27 18:45:53 +0000 2015", "hashtags": [{"text": "INTELCON"}], "user_mentions": [{"screen_name": "gwcchs", "id": 19345085, "name": "GW Cyber & Homeland"}, {"screen_name": "CIA", "id": 2359926157, "name": "CIA"}], "source": "<a href=\"http://twitter.com\" rel=\"nofollow\">Twitter Web Client</a>", "id_str": "659078580266225664", "urls": [], "retrieved": "2017-04-17--14-15-37", "retweet_count": 28, "id": 659078580266225664, "user": {"id": 2359926157}}