{"lang": "en", "media": [{"expanded_url": "https://twitter.com/IARPAnews/status/778248593366982660/photo/1", "display_url": "pic.twitter.com/lWW103scf5", "url": "https://t.co/lWW103scf5", "media_url_https": "https://pbs.twimg.com/media/Cszk5zfWcAAaGSM.jpg", "type": "photo", "id": 778248517353631744, "media_url": "http://pbs.twimg.com/media/Cszk5zfWcAAaGSM.jpg"}], "retweeted_status": {"lang": "en", "text": "IARPA Director, Dr. Jason Matheny, speaking at #INTELCON 2016. https://t.co/lWW103scf5", "created_at": "Tue Sep 20 15:04:58 +0000 2016", "hashtags": [{"text": "INTELCON"}], "user_mentions": [], "source": "<a href=\"http://twitter.com\" rel=\"nofollow\">Twitter Web Client</a>", "id_str": "778248593366982660", "urls": [], "media": [{"expanded_url": "https://twitter.com/IARPAnews/status/778248593366982660/photo/1", "display_url": "pic.twitter.com/lWW103scf5", "url": "https://t.co/lWW103scf5", "media_url_https": "https://pbs.twimg.com/media/Cszk5zfWcAAaGSM.jpg", "type": "photo", "id": 778248517353631744, "media_url": "http://pbs.twimg.com/media/Cszk5zfWcAAaGSM.jpg"}], "retweet_count": 21, "id": 778248593366982660, "favorite_count": 45, "user": {"id": 546007186}}, "deleted": false, "retrieved": "2017-04-17--14-15-36", "created_at": "Tue Sep 20 15:12:06 +0000 2016", "hashtags": [{"text": "INTELCON"}], "user_mentions": [{"screen_name": "IARPAnews", "id": 546007186, "name": "IARPA"}], "source": "<a href=\"http://twitter.com\" rel=\"nofollow\">Twitter Web Client</a>", "id_str": "778250388520701956", "urls": [], "text": "RT @IARPAnews: IARPA Director, Dr. Jason Matheny, speaking at #INTELCON 2016. https://t.co/lWW103scf5", "retweet_count": 21, "id": 778250388520701956, "user": {"id": 2359926157}}