{"lang": "en", "media": [{"expanded_url": "https://twitter.com/CIA/status/778205084442304512/photo/1", "display_url": "pic.twitter.com/b1y372znSo", "url": "https://t.co/b1y372znSo", "media_url_https": "https://pbs.twimg.com/media/Csy9NP5XYAEzNjA.jpg", "type": "photo", "id": 778204870931341313, "media_url": "http://pbs.twimg.com/media/Csy9NP5XYAEzNjA.jpg"}], "deleted": false, "retrieved": "2017-04-17--14-15-36", "created_at": "Tue Sep 20 12:12:05 +0000 2016", "hashtags": [{"text": "INTELCON"}], "user_mentions": [{"screen_name": "gwcchs", "id": 19345085, "name": "GW Cyber & Homeland"}], "source": "<a href=\"http://twitter.com\" rel=\"nofollow\">Twitter Web Client</a>", "id_str": "778205084442304512", "urls": [{"url": "https://t.co/ZO3YTTHXbd", "expanded_url": "https://www.youtube.com/watch?v=sfLGvLyH6Dk&feature=youtu.be"}], "text": "Not attending #INTELCON today? \nIt will be live streamed via @gwcchs @ 9AM EST:\nhttps://t.co/ZO3YTTHXbd https://t.co/b1y372znSo", "retweet_count": 71, "id": 778205084442304512, "favorite_count": 125, "user": {"id": 2359926157}}