{"lang": "en", "retweeted_status": {"lang": "en", "text": "Nick Warner: Pace of tech change is not slowing down; as result, business model that has served our service well has to change. #INTELCON", "created_at": "Tue Sep 20 17:49:48 +0000 2016", "hashtags": [{"text": "INTELCON"}], "user_mentions": [], "source": "<a href=\"http://twitter.com\" rel=\"nofollow\">Twitter Web Client</a>", "id_str": "778290077109813248", "urls": [], "retweet_count": 11, "id": 778290077109813248, "favorite_count": 25, "user": {"id": 19345085}}, "deleted": false, "text": "RT @gwcchs: Nick Warner: Pace of tech change is not slowing down; as result, business model that has served our service well has to change.\u2026", "created_at": "Tue Sep 20 17:50:46 +0000 2016", "hashtags": [], "user_mentions": [{"screen_name": "gwcchs", "id": 19345085, "name": "GW Cyber & Homeland"}], "source": "<a href=\"http://twitter.com\" rel=\"nofollow\">Twitter Web Client</a>", "id_str": "778290317636304900", "urls": [], "retrieved": "2017-04-17--14-15-36", "retweet_count": 11, "id": 778290317636304900, "user": {"id": 2359926157}}