{"lang": "en", "deleted": false, "text": "Born in Binghamton NY, Leslianne moved to Washington when she was 2. She graduated w honors from @PuyallupVikings HS in 1986.\n#inmemoriam", "created_at": "Wed Nov 23 19:17:44 +0000 2016", "hashtags": [{"text": "inmemoriam"}], "user_mentions": [{"screen_name": "PuyallupVikings", "id": 1669010984, "name": "Puyallup High School"}], "source": "<a href=\"http://twitter.com\" rel=\"nofollow\">Twitter Web Client</a>", "in_reply_to_status_id": 801504733240459264, "id_str": "801505029324730369", "in_reply_to_screen_name": "CIA", "user": {"id": 2359926157}, "urls": [], "retrieved": "2017-04-17--14-15-36", "retweet_count": 26, "id": 801505029324730369, "favorite_count": 48, "in_reply_to_user_id": 2359926157}