{"lang": "en", "retweeted_status": {"lang": "en", "text": "FBI claims that when they deploy malware, it magically ceases to be \"malware\" because \"mal\" = \"bad\" &amp; FBI is good. https://t.co/LKKVEc27Ry", "created_at": "Tue Jul 12 16:23:55 +0000 2016", "hashtags": [], "user_mentions": [], "source": "<a href=\"http://twitter.com/#!/download/ipad\" rel=\"nofollow\">Twitter for iPad</a>", "id_str": "752901310110953472", "urls": [], "media": [{"expanded_url": "https://twitter.com/normative/status/752901310110953472/photo/1", "display_url": "pic.twitter.com/LKKVEc27Ry", "url": "https://t.co/LKKVEc27Ry", "media_url_https": "https://pbs.twimg.com/media/CnLXv2sWEAEH-A8.jpg", "type": "photo", "id": 752901304859627521, "media_url": "http://pbs.twimg.com/media/CnLXv2sWEAEH-A8.jpg"}], "retweet_count": 1214, "id": 752901310110953472, "favorite_count": 965, "user": {"id": 8548612}}, "deleted": false, "text": "RT @normative: FBI claims that when they deploy malware, it magically ceases to be \"malware\" because \"mal\" = \"bad\" &amp; FBI is good. https://t\u2026", "created_at": "Wed Jul 13 00:16:45 +0000 2016", "hashtags": [], "user_mentions": [{"screen_name": "normative", "id": 8548612, "name": "Julian Sanchez"}], "source": "<a href=\"http://twitter.com\" rel=\"nofollow\">Twitter Web Client</a>", "id_str": "753020302033125377", "urls": [], "retrieved": "2017-04-17--14-15-12", "retweet_count": 1214, "id": 753020302033125377, "user": {"id": 563819203}}