{"lang": "und", "deleted": false, "text": "#debatenight https://t.co/WaBlmnCYFs", "created_at": "Mon Sep 26 21:15:20 +0000 2016", "hashtags": [{"text": "debatenight"}], "user_mentions": [], "source": "<a href=\"http://twitter.com\" rel=\"nofollow\">Twitter Web Client</a>", "id_str": "780516126216351745", "urls": [{"url": "https://t.co/WaBlmnCYFs", "expanded_url": "https://twitter.com/HeaneyDaily/status/780513804576780290"}], "retrieved": "2017-04-17--14-15-11", "retweet_count": 4, "id": 780516126216351745, "favorite_count": 6, "user": {"id": 563819203}}