{"lang": "und", "media": [{"expanded_url": "https://twitter.com/benwizner/status/782669289325289476/photo/1", "display_url": "pic.twitter.com/xDOsjTcyMF", "url": "https://t.co/xDOsjTcyMF", "media_url_https": "https://pbs.twimg.com/media/CtyZfihWEAAGXwV.jpg", "type": "photo", "id": 782669202377281536, "media_url": "http://pbs.twimg.com/media/CtyZfihWEAAGXwV.jpg"}], "deleted": false, "retrieved": "2017-04-17--14-15-11", "created_at": "Sun Oct 02 19:51:14 +0000 2016", "hashtags": [], "user_mentions": [], "source": "<a href=\"http://twitter.com\" rel=\"nofollow\">Twitter Web Client</a>", "id_str": "782669289325289476", "urls": [], "text": "@EuniceACLU https://t.co/xDOsjTcyMF", "id": 782669289325289476, "favorite_count": 1, "user": {"id": 563819203}}