{"lang": "en", "retweeted_status": {"lang": "en", "text": "There have been governments through history with people like Kushner in power; they just haven't been democracies. https://t.co/UP77yW0USA", "created_at": "Mon Jan 09 23:09:06 +0000 2017", "hashtags": [], "user_mentions": [], "source": "<a href=\"http://www.socialflow.com\" rel=\"nofollow\">SocialFlow</a>", "id_str": "818595481160925184", "urls": [{"url": "https://t.co/UP77yW0USA", "expanded_url": "https://interc.pt/2iXBEbd"}], "retweet_count": 578, "id": 818595481160925184, "favorite_count": 583, "user": {"id": 2329066872}}, "deleted": false, "text": "RT @theintercept: There have been governments through history with people like Kushner in power; they just haven't been democracies. https:\u2026", "created_at": "Mon Jan 09 23:10:48 +0000 2017", "hashtags": [], "user_mentions": [{"screen_name": "theintercept", "id": 2329066872, "name": "The Intercept"}], "source": "<a href=\"http://twitter.com\" rel=\"nofollow\">Twitter Web Client</a>", "id_str": "818595911186153474", "urls": [], "retrieved": "2017-04-17--14-15-11", "retweet_count": 578, "id": 818595911186153474, "user": {"id": 563819203}}