{"lang": "en", "deleted": false, "text": "@Susan_Hennessey Interesting, thanks.", "created_at": "Thu Jan 19 14:16:33 +0000 2017", "hashtags": [], "user_mentions": [{"screen_name": "Susan_Hennessey", "id": 7855062, "name": "Susan Hennessey"}], "source": "<a href=\"http://twitter.com\" rel=\"nofollow\">Twitter Web Client</a>", "in_reply_to_status_id": 822085217489997827, "id_str": "822085341200977920", "in_reply_to_screen_name": "Susan_Hennessey", "user": {"id": 563819203}, "urls": [], "retrieved": "2017-04-17--14-15-11", "id": 822085341200977920, "in_reply_to_user_id": 7855062}